htmdec_formats/__init__.py
htmdec_formats/__main__.py
htmdec_formats/arpes_formats.py
htmdec_formats/cli.py
htmdec_formats/indenter_formats.py
htmdec_formats/indenter_types.py
htmdec_formats/keyence_formats.py
htmdec_formats/ksy_files/dotnet.ksy
htmdec_formats/ksy_files/dotnetlist.py
htmdec_formats/ksy_files/nmdfile.ksy
htmdec_formats/ksy_files/nmdfile.py
htmdec_formats/ksy_files/pxtfile.ksy
htmdec_formats/ksy_files/pxtfile.py
htmdec_formats/ksy_files/simple_xls.ksy
htmdec_formats/ksy_files/simple_xls.py
htmdec_formats/ksy_files/vk4.ksy
htmdec_formats/ksy_files/vk4.py
htmdec_formats/utils/__init__.py
htmdec_formats/utils/convert.py
htmdec_formats-0.1.1.post1.dist-info/AUTHORS.rst
htmdec_formats-0.1.1.post1.dist-info/LICENSE
htmdec_formats-0.1.1.post1.dist-info/METADATA
htmdec_formats-0.1.1.post1.dist-info/WHEEL
htmdec_formats-0.1.1.post1.dist-info/entry_points.txt
htmdec_formats-0.1.1.post1.dist-info/top_level.txt
htmdec_formats-0.1.1.post1.dist-info/RECORD
