Metadata-Version: 2.2
Name: htmdec_formats
Version: 0.1.1.post1
Summary: Basic format conversion for HTMDEC-relevant data
Author-email: Matthew Turk <matthewturk@gmail.com>
Maintainer-email: Matthew Turk <matthewturk@gmail.com>
License: MIT license
Project-URL: bugs, https://github.com/htmdec/htmdec_formats/issues
Project-URL: changelog, https://github.com/htmdec/htmdec_formats/blob/master/changelog.md
Project-URL: homepage, https://github.com/htmdec/htmdec_formats
License-File: LICENSE
License-File: AUTHORS.rst
Requires-Dist: typer
Requires-Dist: kaitaistruct
Requires-Dist: pandas
Requires-Dist: numpy
Requires-Dist: xlsxwriter
Requires-Dist: unyt
Requires-Dist: matplotlib
Provides-Extra: dev
Requires-Dist: coverage; extra == "dev"
Requires-Dist: mypy; extra == "dev"
Requires-Dist: pytest; extra == "dev"
Requires-Dist: ruff; extra == "dev"
